booleano-1.1a2-py3.5-nspkg.pth
booleano/exc.py
booleano/utils.py
booleano/operations/__init__.py
booleano/operations/converters.py
booleano/operations/core.py
booleano/operations/operators.py
booleano/operations/variables.py
booleano/operations/operands/__init__.py
booleano/operations/operands/classes.py
booleano/operations/operands/constants.py
booleano/operations/operands/core.py
booleano/operations/operands/placeholders.py
booleano/parser/__init__.py
booleano/parser/core.py
booleano/parser/grammar.py
booleano/parser/parsers.py
booleano/parser/scope.py
booleano/parser/symbol_table_builder.py
booleano/parser/testutils.py
booleano/parser/trees.py
booleano-1.1a2.dist-info/DESCRIPTION.rst
booleano-1.1a2.dist-info/METADATA
booleano-1.1a2.dist-info/RECORD
booleano-1.1a2.dist-info/WHEEL
booleano-1.1a2.dist-info/metadata.json
booleano-1.1a2.dist-info/namespace_packages.txt
booleano-1.1a2.dist-info/top_level.txt
