Metadata-Version: 2.0
Name: booleano
Version: 1.1a2
Summary: Boolean Expressions Interpreter
Home-page: https://github.com/Yupeek/booleano
Author: Gustavo Narea
Author-email: me@gustavonarea.net
License: MIT X License (http://www.opensource.org/licenses/mit-license.php)
Download-URL: https://github.com/Yupeek/booleano
Keywords: boolean expression natural language condition conditions
Platform: UNKNOWN
Classifier: Development Status :: 3 - Alpha
Classifier: Intended Audience :: Developers
Classifier: License :: OSI Approved :: MIT License
Classifier: Natural Language :: English
Classifier: Operating System :: OS Independent
Classifier: Programming Language :: Python :: 2
Classifier: Programming Language :: Python :: 2.7
Classifier: Programming Language :: Python :: 3.4
Classifier: Programming Language :: Python :: 3.5
Classifier: Programming Language :: Python :: 3.6
Classifier: Topic :: Scientific/Engineering :: Human Machine Interfaces
Classifier: Topic :: Software Development :: Libraries
Classifier: Topic :: Text Processing :: Linguistic
Requires-Dist: pyparsing (>=1.5.2)
Requires-Dist: six
